Metadata-Version: 1.1
Name: sxytools
Version: 0.0.5
Summary: sxy python script
Home-page: https://github.com/shenxiaoyang/sxytools.git
Author: shenxiaoyang
Author-email: 380944919@infocore.cn
License: GPLv3
Download-URL: https://github.com/shenxiaoyang/sxytools.git
Keywords: sxytools
Platform: UNKNOWN
